{
    "fields": [
        {
            "reference": "ROOT",
            "text": "Thank you for calling Equinix Peninsula, the world's largest IBX data center and colocation provider offering the fastest application performance and lowest latency routes worldwide."
        },
        {
            "reference": "ROOT:1",
            "text": "For sales and new colocation deployments, press [INDEX]."
        },
        {
            "reference": "ROOT:2",
            "text": "For technical support and customer service, press [INDEX]."
        },
        {
            "reference": "ROOT:1:1",
            "text": "For information on rack space, power, and cooling, press [INDEX]."
        },
        {
            "reference": "ROOT:1:2",
            "text": "For interconnection and peering services, press [INDEX]."
        },
        {
            "reference": "ROOT:2:1",
            "text": "For technical support and network monitoring, press [INDEX]."
        },
        {
            "reference": "ROOT:2:2",
            "text": "For billing, invoicing, and account management, press [INDEX]."
        },
        {
            "reference": "ROOT:1:1:0",
            "text": "Please hold while we connect you to a sales specialist for colocation capacity and power services."
        },
        {
            "reference": "ROOT:1:2:0",
            "text": "Please hold while we connect you to our interconnection team for peering services."
        },
        {
            "reference": "ROOT:2:1:0",
            "text": "Please hold while we connect you to technical support. An engineer will assist you shortly."
        },
        {
            "reference": "ROOT:2:2:0",
            "text": "Please hold while we connect you to billing and account management."
        }
    ]
}