{
    "fields": [
        {
            "reference": "ROOT",
            "text": "Thank you for calling Carta, the equity management platform trusted by thousands of founders, investors, and employees."
        },
        {
            "reference": "ROOT:1",
            "text": "Press '[INDEX]' for Customer Support, including cap table management and equity questions."
        },
        {
            "reference": "ROOT:1:1",
            "text": "Press '[INDEX]' for Cap Table and Ownership Inquiries."
        },
        {
            "reference": "ROOT:1:1:0",
            "text": "All of our equity specialists are currently assisting other customers. Please hold and we will connect you as soon as possible."
        },
        {
            "reference": "ROOT:1:2",
            "text": "Press '[INDEX]' for Tax Forms and Compliance Support."
        },
        {
            "reference": "ROOT:1:2:0",
            "text": "You have reached our tax and compliance team. Please hold the line and a specialist will be with you shortly."
        },
        {
            "reference": "ROOT:2",
            "text": "Press '[INDEX]' for Sales and New Account Setup."
        },
        {
            "reference": "ROOT:2:1",
            "text": "Press '[INDEX]' for Pricing and Plan Details."
        },
        {
            "reference": "ROOT:2:1:0",
            "text": "One moment please, connecting you to a sales representative to discuss plan options and pricing."
        },
        {
            "reference": "ROOT:2:2",
            "text": "Press '[INDEX]' for Onboarding and Setup Guidance."
        },
        {
            "reference": "ROOT:2:2:0",
            "text": "An onboarding specialist will be with you shortly to help set up your Carta account. Thank you for your patience."
        }
    ]
}