{
    "fields": [
        {
            "reference": "ROOT",
            "text": "Welcome to Greenhouse Software in San Francisco, where we make recruiting your competitive advantage."
        },
        {
            "reference": "ROOT:1",
            "text": "For sales and new customer inquiries, press [INDEX]."
        },
        {
            "reference": "ROOT:1:1",
            "text": "To schedule a live demo of our talent acquisition platform, press [INDEX]."
        },
        {
            "reference": "ROOT:1:1:0",
            "text": "Thank you for your interest in Greenhouse. One moment please as we connect you to a Greenhouse Software Demo Specialist."
        },
        {
            "reference": "ROOT:1:2",
            "text": "To discuss pricing, licensing, and implementation, press [INDEX]."
        },
        {
            "reference": "ROOT:1:2:0",
            "text": "Thank you. Please hold while we connect you to our Sales Solutions team."
        },
        {
            "reference": "ROOT:2",
            "text": "For technical support, account management, and training, press [INDEX]."
        },
        {
            "reference": "ROOT:2:1",
            "text": "For technical support and troubleshooting, press [INDEX]."
        },
        {
            "reference": "ROOT:2:1:0",
            "text": "Your call is important to us. Please hold while we connect you to Technical Support."
        },
        {
            "reference": "ROOT:2:2",
            "text": "For account management, renewals, and customer training, press [INDEX]."
        },
        {
            "reference": "ROOT:2:2:0",
            "text": "Please hold while we connect you to your Account Manager. Thank you for choosing Greenhouse Software."
        }
    ]
}