{
    "fields": [
        {
            "reference": "ROOT",
            "text": "Thank you for calling TaskRabbit, serving San Francisco with over 60,000 vetted Taskers ready to help you."
        },
        {
            "reference": "ROOT:1",
            "text": "To book a Tasker for your next job, press [INDEX]."
        },
        {
            "reference": "ROOT:1:1",
            "text": "For household and cleaning services, press [INDEX]."
        },
        {
            "reference": "ROOT:1:1:0",
            "text": "Please hold while we connect you to our household and cleaning specialists."
        },
        {
            "reference": "ROOT:1:2",
            "text": "For furniture assembly and handyman services, press [INDEX]."
        },
        {
            "reference": "ROOT:1:2:0",
            "text": "Please hold while we connect you to our furniture assembly and handyman experts."
        },
        {
            "reference": "ROOT:2",
            "text": "For customer support and existing tasks, press [INDEX]."
        },
        {
            "reference": "ROOT:2:1",
            "text": "For help with order status and billing inquiries, press [INDEX]."
        },
        {
            "reference": "ROOT:2:1:0",
            "text": "Please hold while we connect you to our billing and order status team."
        },
        {
            "reference": "ROOT:2:2",
            "text": "To cancel or modify an existing task, press [INDEX]."
        },
        {
            "reference": "ROOT:2:2:0",
            "text": "Please hold while we connect you to our task cancellation and modification team."
        }
    ]
}