{
    "fields": [
        {
            "reference": "ROOT",
            "text": "Thank you for calling Trulia in San Francisco, where you can discover a place you\u2019ll love to live."
        },
        {
            "reference": "ROOT:1",
            "text": "To search for homes and apartments, press [INDEX]."
        },
        {
            "reference": "ROOT:1:1",
            "text": "To search by city name, press [INDEX]."
        },
        {
            "reference": "ROOT:1:1:0",
            "text": "Please hold while we retrieve listings for your selected city."
        },
        {
            "reference": "ROOT:1:2",
            "text": "To search by ZIP code, press [INDEX]."
        },
        {
            "reference": "ROOT:1:2:0",
            "text": "Please hold while we retrieve listings for your selected ZIP code."
        },
        {
            "reference": "ROOT:2",
            "text": "For customer support, press [INDEX]."
        },
        {
            "reference": "ROOT:2:1",
            "text": "For account and login assistance, press [INDEX]."
        },
        {
            "reference": "ROOT:2:1:0",
            "text": "Please hold while we connect you to an account specialist."
        },
        {
            "reference": "ROOT:2:2",
            "text": "For feedback or other inquiries, press [INDEX]."
        },
        {
            "reference": "ROOT:2:2:0",
            "text": "Please hold while we connect you to our customer service team."
        }
    ]
}