{
    "fields": [
        {
            "reference": "ROOT",
            "text": "Welcome to Naytev, your San Francisco based secret weapon for Facebook and Instagram A/B testing."
        },
        {
            "reference": "ROOT:1",
            "text": "For support with your A/B testing campaigns, press [INDEX]."
        },
        {
            "reference": "ROOT:2",
            "text": "For sales and new business inquiries, press [INDEX]."
        },
        {
            "reference": "ROOT:1:1",
            "text": "For technical support and troubleshooting, press [INDEX]."
        },
        {
            "reference": "ROOT:1:2",
            "text": "For account management and billing questions, press [INDEX]."
        },
        {
            "reference": "ROOT:1:1:0",
            "text": "Please hold and we will connect you to our technical support team shortly."
        },
        {
            "reference": "ROOT:1:2:0",
            "text": "Please hold and we will connect you to our billing and account specialists shortly."
        },
        {
            "reference": "ROOT:2:1",
            "text": "For product demos and trial setup assistance, press [INDEX]."
        },
        {
            "reference": "ROOT:2:2",
            "text": "For partnership opportunities and marketing collaborations, press [INDEX]."
        },
        {
            "reference": "ROOT:2:1:0",
            "text": "Please hold and we will connect you with a sales representative for demos and trials."
        },
        {
            "reference": "ROOT:2:2:0",
            "text": "Please hold and we will connect you with our partnerships and media inquiry team."
        }
    ]
}